{
  "run_id": "69fab794-1822-4185-b0a1-76b512c3717d",
  "created_at": "2026-03-26T22:18:57.819336+00:00",
  "event_count": 3,
  "events": [
    {
      "run_id": "69fab794-1822-4185-b0a1-76b512c3717d",
      "event": "route_input_received",
      "timestamp": "2026-03-26T22:18:57.819174+00:00",
      "pipeline_mode": "voi",
      "request": {
        "od_ambiguity_index": 0.036667,
        "od_ambiguity_confidence": 0.864,
        "od_engine_disagreement_prior": 0.32603,
        "od_hard_case_prior": 0.331127,
        "od_ambiguity_source_count": 2,
        "od_ambiguity_source_mix": "{\"historical_results_bootstrap\":8,\"routing_graph_probe\":2}",
        "od_ambiguity_source_mix_count": 2,
        "od_ambiguity_source_entropy": 0.721928,
        "od_ambiguity_support_ratio": 0.474005,
        "od_ambiguity_prior_strength": 0.036667,
        "od_ambiguity_family_density": 0.181818,
        "od_ambiguity_margin_pressure": 0.0,
        "od_ambiguity_spread_pressure": 0.0,
        "od_ambiguity_toll_instability": 0.0,
        "od_candidate_path_count": 11,
        "od_corridor_family_count": 2,
        "od_objective_spread": 0.0,
        "od_nominal_margin_proxy": 1.0,
        "od_toll_disagreement_rate": null,
        "ambiguity_budget_prior": 0.036667,
        "ambiguity_budget_band": "high",
        "origin": {
          "lat": 51.752,
          "lon": -1.2577
        },
        "destination": {
          "lat": 52.2053,
          "lon": 0.1218
        },
        "waypoints": [],
        "vehicle_type": "rigid_hgv",
        "scenario_mode": "no_sharing",
        "max_alternatives": 8,
        "weights": {
          "time": 1.0,
          "money": 1.0,
          "co2": 1.0
        },
        "cost_toggles": {
          "use_tolls": true,
          "fuel_price_multiplier": 1.0,
          "carbon_price_per_kg": 0.0,
          "toll_cost_per_km": 0.0
        },
        "terrain_profile": "flat",
        "stochastic": {
          "enabled": false,
          "seed": 20260323,
          "sigma": 0.08,
          "samples": 25
        },
        "optimization_mode": "expected_value",
        "risk_aversion": 1.0,
        "emissions_context": {
          "fuel_type": "diesel",
          "euro_class": "euro6",
          "ambient_temp_c": 15.0
        },
        "weather": {
          "enabled": false,
          "profile": "clear",
          "intensity": 1.0,
          "apply_incident_uplift": true
        },
        "incident_simulation": {
          "enabled": false,
          "seed": null,
          "dwell_rate_per_100km": 0.8,
          "accident_rate_per_100km": 0.25,
          "closure_rate_per_100km": 0.05,
          "dwell_delay_s": 120.0,
          "accident_delay_s": 480.0,
          "closure_delay_s": 900.0,
          "max_events_per_route": 12
        },
        "departure_time_utc": null,
        "pareto_method": "dominance",
        "epsilon": null,
        "pipeline_mode": "voi",
        "refinement_policy": "dccs",
        "pipeline_seed": 20260323,
        "search_budget": 6,
        "evidence_budget": 2,
        "cert_world_count": 96,
        "certificate_threshold": 0.8,
        "tau_stop": 0.02,
        "evaluation_lean_mode": true
      },
      "request_id": "11c0a1ba-a5d5-4c00-9ad6-22a350483d55",
      "run_seed": 20260323
    },
    {
      "run_id": "69fab794-1822-4185-b0a1-76b512c3717d",
      "event": "route_selected",
      "timestamp": "2026-03-26T22:18:57.819196+00:00",
      "selected_id": "route_2",
      "candidate_count": 6,
      "warning_count": 2,
      "candidate_diagnostics": {
        "raw_count": 11,
        "deduped_count": 11,
        "graph_explored_states": 0,
        "graph_generated_paths": 0,
        "graph_emitted_paths": 0,
        "candidate_budget": 3,
        "graph_effective_max_hops": 0,
        "graph_effective_hops_floor": 0,
        "graph_effective_state_budget_initial": 420000,
        "graph_effective_state_budget": 420000,
        "graph_no_path_reason": "skipped_long_corridor_graph_search",
        "graph_no_path_detail": "Skipped expensive long-corridor graph search and used bounded fallback.",
        "prefetch_total_sources": 0,
        "prefetch_success_sources": 0,
        "prefetch_failed_sources": 0,
        "prefetch_failed_keys": "",
        "prefetch_failed_details": "",
        "prefetch_missing_expected_sources": "",
        "prefetch_rows_json": "",
        "scenario_gate_required_configured": 0,
        "scenario_gate_required_effective": 0,
        "scenario_gate_source_ok_count": 0,
        "scenario_gate_waiver_applied": false,
        "scenario_gate_waiver_reason": "",
        "scenario_gate_source_signal_json": "",
        "scenario_gate_source_reachability_json": "",
        "scenario_gate_road_hint": "",
        "scenario_candidate_family_count": 0,
        "scenario_candidate_jaccard_vs_baseline": 1.0,
        "scenario_candidate_jaccard_threshold": 1.0,
        "scenario_candidate_stress_score": 0.0,
        "scenario_candidate_gate_action": "not_applicable",
        "scenario_edge_scaling_version": "v3_live_transform",
        "precheck_reason_code": "ok",
        "precheck_message": "Graph coverage/connectivity checks passed.",
        "precheck_elapsed_ms": 0.0,
        "precheck_origin_node_id": "213435",
        "precheck_destination_node_id": "104523",
        "precheck_origin_nearest_m": 5.875284626807174,
        "precheck_destination_nearest_m": 0.8541214587910665,
        "precheck_origin_selected_m": 5.875284626807174,
        "precheck_destination_selected_m": 0.8541214587910665,
        "precheck_origin_candidate_count": 256,
        "precheck_destination_candidate_count": 256,
        "precheck_selected_component": 1,
        "precheck_selected_component_size": 15564399,
        "precheck_gate_action": "",
        "graph_retry_attempted": true,
        "graph_retry_state_budget": 420000,
        "graph_retry_outcome": "skipped_reliability_corridor_fast_fallback",
        "graph_rescue_attempted": false,
        "graph_rescue_mode": "not_applicable",
        "graph_rescue_state_budget": 0,
        "graph_rescue_outcome": "not_applicable",
        "prefetch_ms": 0.0,
        "scenario_context_ms": 26.76,
        "graph_search_ms_initial": 0.0,
        "graph_search_ms_retry": 0.0,
        "graph_search_ms_rescue": 0.0,
        "graph_search_ms_supplemental": 0.0,
        "graph_k_raw_cache_hit": true,
        "graph_low_ambiguity_fast_path": true,
        "graph_supported_ambiguity_fast_fallback": false,
        "osrm_refine_ms": 59.47,
        "build_options_ms": 98.92,
        "refinement_policy": "dccs",
        "selected_candidate_count": 3,
        "selected_candidate_ids_json": "[\"193ff02e395abb9b824e8edaafd828932a1e462a\", \"2524483a61471703dbe0946ab16a532ae4f241ae\", \"79a9828ea586076cb6cb32bc265f3f4c97d76619\", \"8fe40d17aefcdf3a167300bfbf41e9bd3d9a3bb3\", \"ace89d6cd550230c99d17367c79e54e73270716a\", \"b22f25870b1c718bad0050c3957a1678790c357a\", \"bc50d7c2ca841a22de9352a37a764eb6e5efbdab\", \"df4668e8e64238f74831c3189c6e27144fcf8c30\", \"f35c5c29cab148039e2fe6d5d7f21d536cc8c3bc\", \"f3da8f80a4feb89747e684c4977af5a8e502da5b\", \"f77042b0c873f41d86543f7d0fb9762e4d08e2d6\"]",
        "diversity_collapse_detected": false,
        "diversity_collapse_reason": "",
        "raw_corridor_family_count": 1,
        "refined_corridor_family_count": 11,
        "supplemental_challenger_activated": false,
        "supplemental_candidate_count": 0,
        "supplemental_selected_count": 0,
        "supplemental_budget_used": 0,
        "supplemental_sources_json": "[]",
        "preemptive_comparator_seed_activated": false,
        "preemptive_comparator_candidate_count": 0,
        "preemptive_comparator_source_count": 0,
        "preemptive_comparator_sources_json": "[]",
        "option_build_cache_hits": 0,
        "option_build_cache_misses": 1,
        "option_build_rebuild_count": 1,
        "option_build_reuse_rate": 0.0
      }
    },
    {
      "run_id": "69fab794-1822-4185-b0a1-76b512c3717d",
      "event": "artifacts_written",
      "timestamp": "2026-03-26T22:18:57.819296+00:00",
      "manifest": "out\\manifests\\69fab794-1822-4185-b0a1-76b512c3717d.json",
      "artifact_names": [
        "certificate_summary.json",
        "competitor_fragility_breakdown.json",
        "dccs_candidates.jsonl",
        "dccs_summary.json",
        "evidence_snapshot_manifest.json",
        "evidence_validation.json",
        "final_route_trace.json",
        "initial_certificate_summary.json",
        "initial_competitor_fragility_breakdown.json",
        "initial_route_fragility_map.json",
        "initial_sampled_world_manifest.json",
        "initial_value_of_refresh.json",
        "refined_routes.jsonl",
        "results.csv",
        "results.json",
        "results_summary.csv",
        "route_fragility_map.json",
        "routes.geojson",
        "sampled_world_manifest.json",
        "strict_frontier.jsonl",
        "value_of_refresh.json",
        "voi_action_scores.csv",
        "voi_action_trace.json",
        "voi_controller_state.jsonl",
        "voi_stop_certificate.json",
        "winner_summary.json"
      ]
    }
  ]
}